netznoe_smartmeter_portal_api/__init__.py
netznoe_smartmeter_portal_api/api.py
netznoe_smartmeter_portal_api/models.py
netznoe_smartmeter_portal_api-1.2.0.dist-info/LICENSE
netznoe_smartmeter_portal_api-1.2.0.dist-info/METADATA
netznoe_smartmeter_portal_api-1.2.0.dist-info/WHEEL
netznoe_smartmeter_portal_api-1.2.0.dist-info/top_level.txt
netznoe_smartmeter_portal_api-1.2.0.dist-info/RECORD
