Metadata-Version: 2.1
Name: netznoe-smartmeter-portal-api
Version: 1.2.0
Summary: An unofficial python implementation of the NetzNÖ Smartmeter Portal API
Home-page: https://github.com/schue30/NetzNoe-SmartmeterPortal-Api
Author: Mathias Schuepany
License: MIT
Classifier: Programming Language :: Python
Classifier: Programming Language :: Python :: 3
Classifier: Development Status :: 5 - Production/Stable
Classifier: Intended Audience :: Developers
Classifier: License :: OSI Approved :: MIT License
Requires-Python: >=3.7
License-File: LICENSE
Requires-Dist: requests
